MANIFEST.in
README.rst
setup.py
ESTester.egg-info/PKG-INFO
ESTester.egg-info/SOURCES.txt
ESTester.egg-info/dependency_links.txt
ESTester.egg-info/requires.txt
ESTester.egg-info/top_level.txt
estester/__init__.py