Metadata-Version: 1.1
Name: ESTester
Version: 1.1.0
Summary: Utilities for testing ElasticSearch queries
Home-page: http://github.com/tatiana/estester
Author: Tatiana Al-Chueyr Pereira Martins
Author-email: tatiana.alchueyr@gmail.com
License: GNU GPLv2
Download-URL: http://pypi.python.org/pypi/ESTester
Platform: UNKNOWN
Classifier: Development Status :: 5 - Production/Stable
Classifier: Environment :: Web Environment
Classifier: Intended Audience :: Developers
Classifier: Operating System :: OS Independent
Classifier: Programming Language :: Python
